asmesh-0.0.1.dist-info/licenses/LICENSE
meshsdk/MRDarkTheme.json
meshsdk/MRLightTheme.json
meshsdk/NotoSansSC-Regular.otf
meshsdk/__init__.py
meshsdk/fa-solid-900.ttf
meshsdk/libpybind11nonlimitedapi_meshsdk_3.11.so
meshsdk/libpybind11nonlimitedapi_meshsdk_3.12.so
meshsdk/libpybind11nonlimitedapi_meshsdk_3.13.so
meshsdk/mrcudapy.pyi
meshsdk/mrcudapy.so
meshsdk/mrmeshnumpy.pyi
meshsdk/mrmeshnumpy.so
meshsdk/mrmeshpy.pyi
meshsdk/mrmeshpy.so
meshsdk/mrviewerpy.pyi
meshsdk/mrviewerpy.so
meshsdk/resource/independent_icons/X1/Plane Import.png
meshsdk/resource/independent_icons/X1/Plane XY.png
meshsdk/resource/independent_icons/X1/Plane XZ.png
meshsdk/resource/independent_icons/X1/Plane YZ.png
meshsdk/resource/independent_icons/X1/mouse left.png
meshsdk/resource/independent_icons/X1/mouse right.png
meshsdk/resource/independent_icons/X1/mouse scroll.png
meshsdk/resource/independent_icons/X3/Plane Import.png
meshsdk/resource/independent_icons/X3/Plane XY.png
meshsdk/resource/independent_icons/X3/Plane XZ.png
meshsdk/resource/independent_icons/X3/Plane YZ.png
meshsdk/resource/independent_icons/X3/mouse left.png
meshsdk/resource/independent_icons/X3/mouse right.png
meshsdk/resource/independent_icons/X3/mouse scroll.png
meshsdk/resource/object_icons/X1/AngleMeasurementObject.png
meshsdk/resource/object_icons/X1/CircleObject.png
meshsdk/resource/object_icons/X1/ConeObject.png
meshsdk/resource/object_icons/X1/CylinderObject.png
meshsdk/resource/object_icons/X1/DistanceMeasurementObject.png
meshsdk/resource/object_icons/X1/LineObject.png
meshsdk/resource/object_icons/X1/Object.png
meshsdk/resource/object_icons/X1/ObjectDistanceMap.png
meshsdk/resource/object_icons/X1/ObjectGcode.png
meshsdk/resource/object_icons/X1/ObjectLabel.png
meshsdk/resource/object_icons/X1/ObjectLines.png
meshsdk/resource/object_icons/X1/ObjectMesh.png
meshsdk/resource/object_icons/X1/ObjectPoints.png
meshsdk/resource/object_icons/X1/ObjectVoxels.png
meshsdk/resource/object_icons/X1/Object_open.png
asmesh-0.0.1.dist-info/METADATA
asmesh-0.0.1.dist-info/WHEEL
asmesh-0.0.1.dist-info/top_level.txt
asmesh-0.0.1.dist-info/RECORD
