Metadata-Version: 2.4
Name: asmesh
Version: 0.0.1
Summary: 3D processing library
Author-email: alpinebuster <imzqqq@hotmail.com>
License: NON-COMMERCIAL & education LICENSE AGREEMENT
Project-URL: Homepage, https://meshsdk.tech/
Project-URL: Documentation, https://meshsdk.tech/documentation/
Project-URL: Source, https://github.com/alpinebuster/meshsdk
Project-URL: Bug Reports, https://github.com/alpinebuster/meshsdk/issues
Classifier: Programming Language :: Python :: 3.8
Classifier: Programming Language :: Python :: 3.9
Classifier: Programming Language :: Python :: 3.10
Classifier: Programming Language :: Python :: 3.11
Classifier: Programming Language :: Python :: 3.12
Classifier: Programming Language :: Python :: 3.13
Classifier: License :: Free For Educational Use
Classifier: License :: Free for non-commercial use
Classifier: Operating System :: Microsoft :: Windows
Classifier: Operating System :: POSIX :: Linux
Classifier: Operating System :: MacOS :: MacOS X
Requires-Python: >=3.8
License-File: LICENSE
Requires-Dist: numpy>=1.19.0
Dynamic: license-file
